{
  "repo_root": "/users/akim2/smt-gem5",
  "gem5_bin": "/users/akim2/smt-gem5/gem5/build/X86/gem5.opt",
  "config_script": "/users/akim2/smt-gem5/configs/smt_baseline.py",
  "results_root": "/users/akim2/smt-gem5/results/phase1_runs_pilot",
  "mem_size": "512MB",
  "cpu_clock": "2GHz",
  "max_ticks": 5000000000,

  "workloads": {
    "swaptions_a1": {
      "cmd": "/users/akim2/smt-gem5/parsec/pkgs/apps/swaptions/inst/amd64-linux.gcc-pthreads/bin/swaptions",
      "options": "-ns 8 -sm 2000 -nt 1",
      "domain": "A"
    },
    "swaptions_a2": {
      "cmd": "/users/akim2/smt-gem5/parsec/pkgs/apps/swaptions/inst/amd64-linux.gcc-pthreads/bin/swaptions",
      "options": "-ns 8 -sm 2000 -nt 1",
      "domain": "A"
    },
    "streamcluster_b1": {
      "cmd": "/users/akim2/smt-gem5/parsec/pkgs/kernels/streamcluster/inst/amd64-linux.gcc-pthreads/bin/streamcluster",
      "options": "10 20 32 512 512 100 none output.txt 1",
      "domain": "B"
    }
  },

  "pairs": [
    {
      "name": "A_vs_A",
      "w1": "swaptions_a1",
      "w2": "swaptions_a2"
    },
    {
      "name": "A_vs_B",
      "w1": "swaptions_a1",
      "w2": "streamcluster_b1"
    }
  ]
}